geome/__init__.py
geome/anndata2data.py
geome/datamodule.py
geome/transforms.py
geome-0.0.2.dist-info/METADATA
geome-0.0.2.dist-info/WHEEL
geome-0.0.2.dist-info/licenses/LICENSE
geome-0.0.2.dist-info/RECORD
