Metadata-Version: 2.1
Name: geome
Version: 0.0.2
Summary: Geometric Learning for Genome Data
Project-URL: Documentation, https://geome.readthedocs.io/
Project-URL: Source, https://github.com/theislab/geome
Project-URL: Home-page, https://github.com/theislab/geome
Author: Marcella Toth
Maintainer-email: Marcella Toth <toth.marcella@gmail.com>, Selman Ozleyen <syozleyen@gmail.com>
License: MIT License
License-File: LICENSE
Requires-Python: >=3.8
Requires-Dist: anndata
Requires-Dist: numpy
Requires-Dist: pandas
Requires-Dist: pytorch-lightning
Requires-Dist: scipy
Requires-Dist: session-info
Requires-Dist: squidpy
Requires-Dist: torch
Requires-Dist: torch-geometric
Provides-Extra: dev
Requires-Dist: bump2version; extra == 'dev'
Requires-Dist: pre-commit; extra == 'dev'
Requires-Dist: twine>=4.0.2; extra == 'dev'
Provides-Extra: doc
Requires-Dist: furo; extra == 'doc'
Requires-Dist: ipykernel; extra == 'doc'
Requires-Dist: ipython; extra == 'doc'
Requires-Dist: myst-nb; extra == 'doc'
Requires-Dist: sphinx-autodoc-typehints; extra == 'doc'
Requires-Dist: sphinx-book-theme>=0.3.3; extra == 'doc'
Requires-Dist: sphinx-copybutton; extra == 'doc'
Requires-Dist: sphinx>=4; extra == 'doc'
Requires-Dist: sphinxcontrib-bibtex>=1.0.0; extra == 'doc'
Provides-Extra: test
Requires-Dist: pytest; extra == 'test'
Requires-Dist: pytest-cov; extra == 'test'
